MANIFEST.in
setup.py
words
3lwg.egg-info/PKG-INFO
3lwg.egg-info/SOURCES.txt
3lwg.egg-info/dependency_links.txt
3lwg.egg-info/entry_points.txt
3lwg.egg-info/top_level.txt
tlw/__init__.py
tlw/words.txt