Metadata-Version: 1.0
Name: 3lwg
Version: 4.0
Summary: Three Letter Word Game
Home-page: UNKNOWN
Author: UNKNOWN
Author-email: UNKNOWN
License: UNKNOWN
Platform: UNKNOWN
